mopidy_fm/__init__.py
mopidy_fm/ext.conf
mopidy_fm/frontend.py
Mopidy_FM-0.1.0.dist-info/LICENSE
Mopidy_FM-0.1.0.dist-info/METADATA
Mopidy_FM-0.1.0.dist-info/WHEEL
Mopidy_FM-0.1.0.dist-info/entry_points.txt
Mopidy_FM-0.1.0.dist-info/top_level.txt
Mopidy_FM-0.1.0.dist-info/RECORD
